<?xml version="1.0" encoding="UTF-8"?>
<biblioteca>
  <Administrativo>
    <libro id="1001">
      <titulo>Contratos 1</titulo>
      <autor>Contador</autor>
      <editorial>Empresa</editorial>
      <areaConocimiento>Administrativo</areaConocimiento>
      <estado>Disponible</estado>
    </libro>
    <libro id="1002">
      <titulo>Contratos 2</titulo>
      <autor>Contador</autor>
      <editorial>Empresa</editorial>
      <areaConocimiento>Administrativo</areaConocimiento>
      <estado>Disponible</estado>
    </libro>
    <libro id="1003">
      <titulo>Contratos 3</titulo>
      <autor>Contador</autor>
      <editorial>Empresa</editorial>
      <areaConocimiento>Administrativo</areaConocimiento>
      <estado>Disponible</estado>
    </libro>
    <libro id="1004">
      <titulo>Demanda 1</titulo>
      <autor>Abogado</autor>
      <editorial>Empresa</editorial>
      <areaConocimiento>Administrativo</areaConocimiento>
      <estado>Disponible</estado>
    </libro>
    <libro id="1005">
      <titulo>Demanda 2</titulo>
      <autor>Abogado</autor>
      <editorial>Empresa</editorial>
      <areaConocimiento>Administrativo</areaConocimiento>
      <estado>Disponible</estado>
    </libro>
  </Administrativo>
  <Fisica>
    <libro id="1006">
      <titulo>Fisica 1</titulo>
      <autor>J.Alvarez</autor>
      <editorial>Fisicos lati</editorial>
      <areaConocimiento>Fisica</areaConocimiento>
      <estado>Disponible</estado>
    </libro>
  </Fisica>
  <Matematicas>
    <libro id="1007">
      <titulo>Metodos numericos</titulo>
      <autor>Zill</autor>
      <editorial>Inges</editorial>
      <areaConocimiento>Matematicas</areaConocimiento>
      <estado>Disponible</estado>
    </libro>
  </Matematicas>
  <Medicina>
    <libro id="1008">
      <titulo>Anatomia</titulo>
      <autor>Akkerman</autor>
      <editorial>Fisioco</editorial>
      <areaConocimiento>Medicina</areaConocimiento>
      <estado>Disponible</estado>
    </libro>
  </Medicina>
</biblioteca>
